sdc/__init__.py
sdc/auth_frame.py
sdc/error.py
sdc/crypto/__init__.py
sdc/crypto/asymm.py
sdc/crypto/constants.py
sdc/crypto/symm.py
sdc/lib/libgeneration.cpython-310-x86_64-linux-gnu.so
sdc/lib/libverification.cpython-310-x86_64-linux-gnu.so
sdc/ual/__init__.py
sdc/ual/constants.py
sdc/ual/ual.py
sdc_sdk-0.1.0.dev250109.dist-info/METADATA
sdc_sdk-0.1.0.dev250109.dist-info/WHEEL
sdc_sdk-0.1.0.dev250109.dist-info/top_level.txt
sdc_sdk-0.1.0.dev250109.dist-info/RECORD
